pyawd/AcousticWaveDataset.py
pyawd/GenerateVideo.py
pyawd/Marmousi.py
pyawd/VectorAcousticWaveDataset.py
pyawd/VectorAcousticWaveDataset2D.py
pyawd/VectorAcousticWaveDataset3D.py
pyawd/VelocityModel.py
pyawd/VelocityModel2D.py
pyawd/VelocityModel3D.py
pyawd/__init__.py
pyawd/_marmousi_data.py
pyawd/utils.py
pyawd-0.3.85.dist-info/licenses/LICENSE
pyawd-0.3.85.dist-info/METADATA
pyawd-0.3.85.dist-info/WHEEL
pyawd-0.3.85.dist-info/top_level.txt
pyawd-0.3.85.dist-info/RECORD
