Metadata-Version: 2.4
Name: pyawd
Version: 0.3.85
Summary: A Pytorch dataset for Acoustic Wave Propagation
Author-email: Tribel Pascal <pascal.tribel@ulb.be>
Project-URL: Homepage, https://github.com/pascaltribel/PyAWD
Project-URL: Issues, https://github.com/pascaltribel/PyAWD/issues
Classifier: Programming Language :: Python :: 3
Classifier: License :: OSI Approved :: MIT License
Classifier: Operating System :: OS Independent
Requires-Python: >=3.8
License-File: LICENSE
Requires-Dist: devito
Requires-Dist: torch
Requires-Dist: matplotlib
Requires-Dist: tqdm
Requires-Dist: numpy
Requires-Dist: sympy
Requires-Dist: opencv-python
Requires-Dist: pyvista
Requires-Dist: trame
Requires-Dist: vtk
Requires-Dist: imageio
Requires-Dist: imageio-ffmpeg
Requires-Dist: npy-append-array
Requires-Dist: mpi4py
Requires-Dist: opencv-python
Dynamic: license-file
